{
  "k":"vivosmart-HR",
  "title":"vívosmart HR",
  "i":"2016-02-01",
  "a":[
    {
      "e":"p",
      "s":[
        {
          "e":"span",
          "t":"話說最近又看上了一款運動手環！說到運動手環，去年買的 "
        },
        {
          "e":"a",
          "t":"vívosmart",
          "href":"http://www.garmin.com.tw/minisite/vivo/vivosmart/"
        },
        {
          "e":"span",
          "t":" 算是這台 "
        },
        {
          "e":"a",
          "t":"vívosmart HR",
          "href":"http://www.garmin.com.tw/minisite/vivo/vivosmart-hr/"
        },
        {
          "e":"span",
          "t":" 的前身！去年就打算買可以記錄心率的穿戴裝置，但那時坊間有紀錄心率功能的穿戴裝置只有快上萬的運動型手錶才有，要不然就是需要配戴"
        },
        {
          "e":"a",
          "t":"心率帶",
          "href":"http://tw.running.biji.co/index.php?q=news&amp;amp;act=info&amp;amp;id=4935"
        },
        {
          "e":"span",
          "t":"才能紀錄心率，然而唯一有符合我要求的就是 "
        },
        {
          "e":"a",
          "t":"Apple Watch",
          "href":"http://www.apple.com/tw/watch/"
        },
        {
          "e":"span",
          "t":"。"
        }
      ]
    },
    {
      "e":"img",
      "src":"https://www.ioa.tw/img/91f1e976a5dbe85c9dc7a2488e547b67.jpg",
      "alt":"沒有心率感測器的第一代 vívosmart，其實戴起來很舒服喲"
    },
    {
      "e":"img",
      "src":"https://www.ioa.tw/img/c14d9a7df577a1758e481e1979918aae.jpg",
      "alt":"黑色版本的 vívosmart 可是隱藏版的喲"
    },
    {
      "e":"p",
      "s":[
        {
          "e":"span",
          "t":"雖然價格不會是第一考量，但是 Apple Watch 的蓄電量真的是悲劇，所以去年就先買了 vívosmart 使用啦！不過依據去年使用 "
        },
        {
          "e":"a",
          "t":"Garmin",
          "href":"http://www.garmin.com.tw/"
        },
        {
          "e":"span",
          "t":"的 vívosmart 下來，整體心得算是還不錯喔！"
        }
      ]
    },
    {
      "e":"p",
      "t":"怎麼說呢？"
    },
    {
      "e":"p",
      "t":"去年三月買的 vívosmart 在年底時，LED 發生明暗不清的故障狀況(=口=a)，因為還在保固期，所以就將產品寄回公司後，Garmin 不囉唆的立馬直接回來寄一個新的！這一點著實還蠻令人滿意的 ：）"
    },
    {
      "e":"p",
      "s":[
        {
          "e":"span",
          "t":"好啦，不多說廢話！直接進入今天主題啦！前些日子得知 Garmin 在去年底有推出這款 vívosmart HR，而 "
        },
        {
          "e":"b",
          "t":"Hr"
        },
        {
          "e":"span",
          "t":" 這兩個字的意思應該就是 Heart 的意思吧(猜)！就在昨晚天人交戰了一晚之後，今天一早還是決定了！"
        }
      ]
    },
    {
      "e":"p",
      "s":[
        {
          "e":"span",
          "t":"結論就是 "
        },
        {
          "e":"a",
          "t":"PChome 24H",
          "href":"http://24h.pchome.com.tw/"
        },
        {
          "e":"span",
          "t":" 真的是很邪惡耶！！！"
        }
      ]
    },
    {
      "e":"img",
      "src":"https://www.ioa.tw/img/f327734a64ad9c9e34eeded633f326bf.jpg",
      "alt":"早上一訂，下午就到了"
    },
    {
      "e":"img",
      "src":"https://www.ioa.tw/img/ea7f4744952e87854293ba1b17d47e65.jpg",
      "alt":"vívosmart HR 包裝盒，包裝整個就是有質感多了"
    },
    {
      "e":"img",
      "src":"https://www.ioa.tw/img/2c638d21720b9b4169d4ad1319c1782a.jpg",
      "alt":"vívosmart HR 包裝盒背面"
    },
    {
      "e":"p",
      "s":[
        {
          "e":"span",
          "t":"當然，立馬拿起小刀子小心翼翼的拆開它！其實當看到包裝時有意外到，當下真覺得 Garmin 真的的好偏心！為啥 vívosmart HR 的包裝比 vívosmart 還要漂亮，令人有種 Garmin 就是先故意出第一代普通功能的 vívosmart 第二年再推出 vívosmart HR，再撈一次消費者的摳摳的感覺(T___T)，這次的 vívosmart HR 一共推出三種顏色，分別是 "
        },
        {
          "e":"b",
          "t":"黑"
        },
        {
          "e":"span",
          "t":"、"
        },
        {
          "e":"b",
          "t":"藍"
        },
        {
          "e":"span",
          "t":"、"
        },
        {
          "e":"b",
          "t":"紫"
        },
        {
          "e":"span",
          "t":" 三種顏色而這次就先不買黑色了，直覺認為這次藍色好看太多啦！"
        }
      ]
    },
    {
      "e":"img",
      "src":"https://www.ioa.tw/img/89421b2d00c7b1484377bc41b552ad78.jpg",
      "alt":"vívosmart HR 拆開後得內包裝"
    },
    {
      "e":"img",
      "src":"https://www.ioa.tw/img/71b826158f6e0e117dcc46fd389f722a.jpg",
      "alt":"近照，上面還貼著一張心率預覽畫面，可見這次主打就是心率紀錄無誤"
    },
    {
      "e":"img",
      "src":"https://www.ioa.tw/img/929661463b915a69fc0e2565035747b4.jpg",
      "alt":"錶帶也跟上一款不一樣，更像手錶了"
    },
    {
      "e":"img",
      "src":"https://www.ioa.tw/img/66b16e37074caf1746f1537c9fa9ef30.jpg",
      "alt":"背面多了這個！它就是心率感測器"
    },
    {
      "e":"img",
      "src":"https://www.ioa.tw/img/e91514a48bcff7313a9f7bffc53aec5b.jpg",
      "alt":"這次的充電線藏得非常漂亮"
    },
    {
      "e":"p",
      "t":"不過打開看到 USB 傳輸線之後，其實有點冷掉，因為上一代的傳輸線是用\"夾子\"的方式來固定充電，非常牢固！而 vívosmart HR 卻不是，他僅用簡單的凹凸處扣接著，這點真的很怕哪天用久了會磨損、磨平，然後接觸不良。"
    },
    {
      "e":"img",
      "src":"https://www.ioa.tw/img/d7f23544b2f982aa5855e270e7082e17.jpg",
      "alt":"USB 端有著 TAIWAN 的字樣，這點倒是有加分"
    },
    {
      "e":"img",
      "src":"https://www.ioa.tw/img/51e822983b544105d260307018c2a146.jpg",
      "alt":"vívosmart HR 心率感應器燈是綠色的"
    },
    {
      "e":"img",
      "src":"https://www.ioa.tw/img/a441d322979e7c020b40a9b6f8d64f7e.jpg",
      "alt":"充電銜接器得接口也跟 vívosmart 不一樣"
    },
    {
      "e":"img",
      "src":"https://www.ioa.tw/img/bb99df92337e0a28d6c58258b6607133.jpg",
      "alt":"充電銜接器與 vívosmart HR 背面銜接處"
    },
    {
      "e":"img",
      "src":"https://www.ioa.tw/img/6b1c167e69c04e7081a17d3888307222.jpg",
      "alt":"接上 USB 之後的 vívosmart HR"
    },
    {
      "e":"p",
      "t":"接著就是試用囉！照著說明書一步步的啟動，會看到後面的感應燈已經亮起，相對的整個心也跟著亮起！當然，第一件事就是測量一下\"洞姿洞姿\"的心跳聲囉！"
    },
    {
      "e":"p",
      "s":[
        {
          "e":"span",
          "t":"首先，先靜止的坐好，我先用手機 APP "
        },
        {
          "e":"a",
          "t":"Instant Heart Rate",
          "href":"https://itunes.apple.com/tw/app/instant-heart-rate-heart-rate/id409625068?mt=8"
        },
        {
          "e":"span",
          "t":" 測量我手指的感應出來的心率！接著就是看一下我手腕上的 vívosmart HR 嗯！其實只有差一下捏！之後接著測了好幾次，整體上算是蠻準確的，雖然還是會有誤差個一兩下，但我還算滿意！"
        }
      ]
    },
    {
      "e":"img",
      "src":"https://www.ioa.tw/img/3b1a7169b2985faa89d677e18c6def06.jpg",
      "alt":"iOS APP Instant Heart Rate 所測得的靜止心率"
    },
    {
      "e":"img",
      "src":"https://www.ioa.tw/img/ed5d762fd7e0b96534778e2645cc51d1.jpg",
      "alt":"vívosmart HR 心率測試"
    },
    {
      "e":"p",
      "s":[
        {
          "e":"span",
          "t":"以上主要是針對 vívosmart HR 的簡單開箱與心率測試，其實 vívosmart HR 還有很多新功能，例如：計算爬樓梯.. 等！如果各位有興趣可以到"
        },
        {
          "e":"a",
          "t":"官網",
          "href":"http://www.garmin.com.tw/minisite/vivo/vivosmart-hr/"
        },
        {
          "e":"span",
          "t":"看看，小心！別越看越火喔.. XD"
        }
      ]
    }
  ],
  "r":[
    {
      "e":"ul",
      "s":[
        {
          "e":"li",
          "s":[
            {
              "e":"a",
              "t":"vívosmart HR 開箱文 - ZEUS // Design Studio",
              "href":"https://www.zeusdesign.com.tw/article/2-v%C3%ADvosmart%20HR%20%E9%96%8B%E7%AE%B1%E6%96%87.html"
            }
          ]
        }
      ]
    }
  ],
  "g":[
    "開箱",
    "穿戴",
    "手環"
  ]
}